jhsingle_native_proxy/__init__.py
jhsingle_native_proxy/activity.py
jhsingle_native_proxy/conda_runner.py
jhsingle_native_proxy/gitwrapper.py
jhsingle_native_proxy/main.py
jhsingle_native_proxy/proxyhandlers.py
jhsingle_native_proxy/pull.py
jhsingle_native_proxy/util.py
jhsingle_native_proxy/websocket.py
jhsingle_native_proxy-0.8.2.dist-info/LICENSE
jhsingle_native_proxy-0.8.2.dist-info/LICENSE-jupyter-server-proxy
jhsingle_native_proxy-0.8.2.dist-info/LICENSE-nbgitpuller
jhsingle_native_proxy-0.8.2.dist-info/METADATA
jhsingle_native_proxy-0.8.2.dist-info/WHEEL
jhsingle_native_proxy-0.8.2.dist-info/entry_points.txt
jhsingle_native_proxy-0.8.2.dist-info/top_level.txt
jhsingle_native_proxy-0.8.2.dist-info/RECORD
