Metadata-Version: 2.1
Name: jhsingle-native-proxy
Version: 0.8.2
Summary: Wrap an arbitrary webapp so it can be used in place of jupyter-singleuser in a JupyterHub setting
Home-page: https://github.com/ideonate/jhsingle-native-proxy
Author: Dan Lester
Author-email: dan@ideonate.com
License: UNKNOWN
Platform: UNKNOWN
Classifier: Programming Language :: Python :: 3
Classifier: License :: OSI Approved :: MIT License
Classifier: Operating System :: OS Independent
Requires-Python: >=3.6
Requires-Dist: jupyterhub (>=1.0.0)
Requires-Dist: tornado (>=6.0.4)
Requires-Dist: Click (>=7.0)
Requires-Dist: aiohttp
Requires-Dist: simpervisor (~=0.4)
